byzh_rc/__init__.py
byzh_rc/Bbasic/Byzh.py
byzh_rc/Bbasic/__init__.py
byzh_rc/Bbasic/Btext_style/__init__.py
byzh_rc/Bbasic/Btext_style/text_style.py
byzh_rc/Bdeeplearning/__init__.py
byzh_rc/Bdeeplearning/Bdataset/__init__.py
byzh_rc/Bdeeplearning/Bdataset/merge_dataset.py
byzh_rc/Bdeeplearning/Bdataset/standard.py
byzh_rc/Bdeeplearning/Bdemo/__init__.py
byzh_rc/Bdeeplearning/Bdemo/mnist.py
byzh_rc/Bdeeplearning/Bdemo/test.py
byzh_rc/Bdeeplearning/Bearly_stop/__init__.py
byzh_rc/Bdeeplearning/Bearly_stop/reloadbyloss.py
byzh_rc/Bdeeplearning/Bearly_stop/stopbyacc.py
byzh_rc/Bdeeplearning/Bearly_stop/stopbyaccdelta.py
byzh_rc/Bdeeplearning/Bearly_stop/stopbybyzh.py
byzh_rc/Bdeeplearning/Bearly_stop/stopbyloss.py
byzh_rc/Bdeeplearning/Bearly_stop/stopbylossdelta.py
byzh_rc/Bdeeplearning/Bearly_stop/stopbyoverfitting.py
byzh_rc/Bdeeplearning/Blr_schedulers/__init__.py
byzh_rc/Bdeeplearning/Blr_schedulers/decaylr.py
byzh_rc/Bdeeplearning/Blr_schedulers/warmupdecaylr.py
byzh_rc/Bdeeplearning/Blr_schedulers/warmuplr.py
byzh_rc/Bdeeplearning/Bmodel/__init__.py
byzh_rc/Bdeeplearning/Bmodel/lenet5.py
byzh_rc/Bdeeplearning/Bmodel/lstm.py
byzh_rc/Bdeeplearning/Bmodel/resnet18.py
byzh_rc/Bdeeplearning/Bmodel/rnn.py
byzh_rc/Bdeeplearning/Btrainer/__init__.py
byzh_rc/Bdeeplearning/Btrainer/trainer.py
byzh_rc/Bdeeplearning/Butils/__init__.py
byzh_rc/Bdeeplearning/Butils/get_device.py
byzh_rc/Bdeeplearning/Butils/get_flops.py
byzh_rc/Bdeeplearning/Butils/get_gpu.py
byzh_rc/Bdeeplearning/Butils/get_params.py
byzh_rc/Bdeeplearning/Butils/grid_train.py
byzh_rc/Bdeeplearning/Butils/load_model.py
byzh_rc/Bdeeplearning/Bvisual/__init__.py
byzh_rc/Bdeeplearning/Bvisual/draw_confusion_matrix.py
byzh_rc/Bffmpeg/__init__.py
byzh_rc/Bffmpeg/convert.py
byzh_rc/Bmath/__init__.py
byzh_rc/Bmath/divides.py
byzh_rc/Bmath/get_norm.py
byzh_rc/Boffice/__init__.py
byzh_rc/Boffice/Bpdf/__init__.py
byzh_rc/Boffice/Bpdf/pdf2img.py
byzh_rc/Bterminal/__init__.py
byzh_rc/Bterminal/cmd.py
byzh_rc-1.3.40.dist-info/LICENSE
byzh_rc-1.3.40.dist-info/METADATA
byzh_rc-1.3.40.dist-info/WHEEL
byzh_rc-1.3.40.dist-info/top_level.txt
byzh_rc-1.3.40.dist-info/RECORD
