Metadata-Version: 2.1
Name: byzh_rc
Version: 1.3.40
Summary: 更方便的深度学习
Author: byzh_rc
License: MIT
License-File: LICENSE
Requires-Dist: wcwidth
Requires-Dist: thop
Requires-Dist: matplotlib
Requires-Dist: seaborn
